assemblyline_service_server/VERSION
assemblyline_service_server/__init__.py
assemblyline_service_server/app.py
assemblyline_service_server/config.py
assemblyline_service_server/gunicorn_config.py
assemblyline_service_server/healthz.py
assemblyline_service_server/patched.py
assemblyline_service_server/session.py
assemblyline_service_server/api/__init__.py
assemblyline_service_server/api/base.py
assemblyline_service_server/api/v1/__init__.py
assemblyline_service_server/api/v1/badlist.py
assemblyline_service_server/api/v1/file.py
assemblyline_service_server/api/v1/safelist.py
assemblyline_service_server/api/v1/service.py
assemblyline_service_server/api/v1/task.py
assemblyline_service_server/helper/__init__.py
assemblyline_service_server/helper/logger.py
assemblyline_service_server/helper/metrics.py
assemblyline_service_server/helper/response.py
assemblyline_service_server-4.7.0.1.dist-info/licenses/LICENCE.md
assemblyline_service_server-4.7.0.1.dist-info/METADATA
assemblyline_service_server-4.7.0.1.dist-info/WHEEL
assemblyline_service_server-4.7.0.1.dist-info/top_level.txt
assemblyline_service_server-4.7.0.1.dist-info/RECORD
