Metadata-Version: 2.4
Name: assemblyline-service-server
Version: 4.7.0.1
Summary: Assemblyline 4 - Service Server
Home-page: https://github.com/CybercentreCanada/assemblyline-service-server/
Author: CCCS Assemblyline development team
Author-email: assemblyline@cyber.gc.ca
License: MIT
Keywords: assemblyline malware gc canada cse-cst cse cst cyber cccs
Classifier: Development Status :: 5 - Production/Stable
Classifier: Intended Audience :: Developers
Classifier: Topic :: Software Development :: Libraries
Classifier: License :: OSI Approved :: MIT License
Classifier: Programming Language :: Python :: 3.7
Classifier: Programming Language :: Python :: 3.8
Classifier: Programming Language :: Python :: 3.9
Classifier: Programming Language :: Python :: 3.10
Classifier: Programming Language :: Python :: 3.11
Classifier: Programming Language :: Python :: 3.12
License-File: LICENCE.md
Requires-Dist: assemblyline
Requires-Dist: assemblyline-core
Requires-Dist: werkzeug
Requires-Dist: flask
Requires-Dist: flask-socketio
Requires-Dist: gunicorn
Requires-Dist: gevent
Requires-Dist: gevent-websocket
Provides-Extra: test
Requires-Dist: pytest; extra == "test"
Dynamic: author
Dynamic: author-email
Dynamic: classifier
Dynamic: description
Dynamic: description-content-type
Dynamic: home-page
Dynamic: keywords
Dynamic: license
Dynamic: license-file
Dynamic: provides-extra
Dynamic: requires-dist
Dynamic: summary
